<annotation>
	<folder>MnF</folder>
	<filename>IMG_20191003_151432.jpg</filename>
	<path>/home/donalngo/Pictures/MnF/IMG_20191003_151432.jpg</path>
	<source>
		<database>Unknown</database>
	</source>
	<size>
		<width>3968</width>
		<height>2976</height>
		<depth>3</depth>
	</size>
	<segmented>0</segmented>
	<object>
		<name>2</name>
		<pose>Unspecified</pose>
		<truncated>0</truncated>
		<difficult>0</difficult>
		<bndbox>
			<xmin>90</xmin>
			<ymin>594</ymin>
			<xmax>1103</xmax>
			<ymax>2681</ymax>
		</bndbox>
	</object>
	<object>
		<name>2</name>
		<pose>Unspecified</pose>
		<truncated>0</truncated>
		<difficult>0</difficult>
		<bndbox>
			<xmin>888</xmin>
			<ymin>625</ymin>
			<xmax>1774</xmax>
			<ymax>2723</ymax>
		</bndbox>
	</object>
	<object>
		<name>2</name>
		<pose>Unspecified</pose>
		<truncated>0</truncated>
		<difficult>0</difficult>
		<bndbox>
			<xmin>1769</xmin>
			<ymin>498</ymin>
			<xmax>2582</xmax>
			<ymax>2702</ymax>
		</bndbox>
	</object>
	<object>
		<name>2</name>
		<pose>Unspecified</pose>
		<truncated>0</truncated>
		<difficult>0</difficult>
		<bndbox>
			<xmin>2482</xmin>
			<ymin>548</ymin>
			<xmax>3351</xmax>
			<ymax>2696</ymax>
		</bndbox>
	</object>
	<object>
		<name>2</name>
		<pose>Unspecified</pose>
		<truncated>1</truncated>
		<difficult>0</difficult>
		<bndbox>
			<xmin>3190</xmin>
			<ymin>552</ymin>
			<xmax>3968</xmax>
			<ymax>2698</ymax>
		</bndbox>
	</object>
</annotation>
